[{"stockTicker":"UPS","stockName":"United Parcel"},{"stockTicker":"SLB","stockName":"Schlumberger"},{"stockTicker":"VALE","stockName":"Vale"},{"stockTicker":"EXC","stockName":"Exelon"},{"stockTicker":"DAL","stockName":"Delta Air Lines"},{"stockTicker":"AIG","stockName":"American International Group"},{"stockTicker":"SO","stockName":"Southern"},{"stockTicker":"SQ","stockName":"Square"},{"stockTicker":"KMI","stockName":"Kinder Morgan"},{"stockTicker":"SBRA","stockName":"Sabra Healthcare Reit"},{"stockTicker":"RIG","stockName":"Transocean"},{"stockTicker":"NLY","stockName":"Annaly Capital Management"},{"stockTicker":"FB","stockName":"Facebook"},{"stockTicker":"VER","stockName":"Vereit"},{"stockTicker":"KIM","stockName":"Kimco"},{"stockTicker":"PYPL","stockName":"Paypal"},{"stockTicker":"BABA","stockName":"Alibaba"},{"stockTicker":"T","stockName":"AT&T"},{"stockTicker":"VTR","stockName":"Ventas"},{"stockTicker":"SU","stockName":"Suncor Energy"},{"stockTicker":"TGT","stockName":"Target"},{"stockTicker":"MO","stockName":"Altria Group"},{"stockTicker":"ESV","stockName":"Ensco"},{"stockTicker":"GE","stockName":"General Electric"},{"stockTicker":"KO","stockName":"Coca-Cola"},{"stockTicker":"EGP","stockName":"Eastgroup"},{"stockTicker":"M","stockName":"Macy's"},{"stockTicker":"O","stockName":"Realty Income"},{"stockTicker":"STAG","stockName":"Stag Industrial"},{"stockTicker":"AGNC ","stockName":"AGNC Investment"},{"stockTicker":"PLD","stockName":"Prologis"},{"stockTicker":"ARES","stockName":"Ares Management LP"},{"stockTicker":"SNH","stockName":"Senior Housing Properties"},{"stockTicker":"BA","stockName":"Boeing"},{"stockTicker":"ADC","stockName":"Agree Realty Corp."},{"stockTicker":"GOOGL","stockName":"Alphabet Inc class a"},{"stockTicker":"FLOW","stockName":"SPX Flow"},{"stockTicker":"BAC","stockName":"Bank of America"},{"stockTicker":"C","stockName":"Citigroup"},{"stockTicker":"SUN","stockName":"Sunoco Logistics Partner"},{"stockTicker":"FSLR","stockName":"First Solar"},{"stockTicker":"F","stockName":"Ford Motor"},{"stockTicker":"QCOM","stockName":"Qualcomm Incorporated"},{"stockTicker":"TEVA","stockName":"TEVA Pharmaa Industries"},{"stockTicker":"SKT","stockName":"Tanger Factory Outlet"},{"stockTicker":"CGNX","stockName":"Cognex"},{"stockTicker":"MIDD","stockName":"Middleby"},{"stockTicker":"INTC","stockName":"Intel"},{"stockTicker":"MSFT","stockName":"Microsoft"},{"stockTicker":"JNJ","stockName":"Johnson&Johnson"},{"stockTicker":"ROK","stockName":"Rockwell Automation"},{"stockTicker":"AA","stockName":"Alcoa"},{"stockTicker":"WEC","stockName":"WEC Energy Group"},{"stockTicker":"PPC","stockName":"Pilgrims Pride"},{"stockTicker":"COP","stockName":"Conocophilips"},{"stockTicker":"LMT","stockName":"Lockheed Martin"},{"stockTicker":"DIS","stockName":"Walt-Disney"},{"stockTicker":"BXMT","stockName":"Blackstone Mortgage"},{"stockTicker":"GM","stockName":"General Motors"},{"stockTicker":"ANDV","stockName":"Andeavor"},{"stockTicker":"PG","stockName":"Procter&Gamble"},{"stockTicker":"AAPL","stockName":"Apple"},{"stockTicker":"ROLL","stockName":"RBC Bearings"},{"stockTicker":"XOM","stockName":"Exxon Mobile"},{"stockTicker":"DNKN","stockName":"Donkin Donuts"},{"stockTicker":"WMT","stockName":"Wal-Mart"},{"stockTicker":"PSX","stockName":"Phillips 66"},{"stockTicker":"MCD","stockName":"McDonald's"},{"stockTicker":"HAS","stockName":"Hasbro"},{"stockTicker":"JWN","stockName":"Nordstrom"},{"stockTicker":"SBUX","stockName":"Strarbucks"},{"stockTicker":"ABT","stockName":"Abbott Laboratories"},{"stockTicker":"MOS","stockName":"Mosaic"},{"stockTicker":"ULTI","stockName":"The Ultimate Software"},{"stockTicker":"TXN","stockName":"Texas Instruments"},{"stockTicker":"NRG","stockName":"NRG Energie"},{"stockTicker":"XLNX","stockName":"Xilinx"},{"stockTicker":"HLT","stockName":"Hilton Worldwide"},{"stockTicker":"CMI","stockName":"Cummins"},{"stockTicker":"WLK","stockName":"Westlake Chemical"},{"stockTicker":"WSM","stockName":"Williams-Sonoma"},{"stockTicker":"TDC","stockName":"Teradata"},{"stockTicker":"AMZN","stockName":"Amazon"},{"stockTicker":"DLR","stockName":"Digital"},{"stockTicker":"WELL","stockName":"Welltower"},{"stockTicker":"HCP","stockName":"HCP"},{"stockTicker":"IRM","stockName":"iron mountain"},{"stockTicker":"HTA","stockName":"Healthcare of America"},{"stockTicker":"STOR","stockName":"Store Capital"},{"stockTicker":"ABR","stockName":"Arbor"},{"stockTicker":"MPW","stockName":"Medical Properties"},{"stockTicker":"JPM","stockName":"JP Morgan"},{"stockTicker":"V","stockName":"Visa"},{"stockTicker":"WFC","stockName":"Wells Fargo"},{"stockTicker":"HD","stockName":"Home Depot"},{"stockTicker":"VZ","stockName":"Verizon"},{"stockTicker":"CSCO","stockName":"Cisco"},{"stockTicker":"NVS","stockName":"Novartis"},{"stockTicker":"MA","stockName":"Mastercard"},{"stockTicker":"ORCL","stockName":"Oracle"},{"stockTicker":"NVDA","stockName":"Nvidia"},{"stockTicker":"CMCSA","stockName":"Comcast"},{"stockTicker":"PEP","stockName":"Pepsico"},{"stockTicker":"DWDP","stockName":"Dupont"},{"stockTicker":"NFLX","stockName":"Netflix"},{"stockTicker":"ABBV","stockName":"AbbVie"},{"stockTicker":"NKE","stockName":"Nike"},{"stockTicker":"IBM","stockName":"IBM"},{"stockTicker":"PM","stockName":"Phiilip Morris"},{"stockTicker":"MDT","stockName":"Medtronic"},{"stockTicker":"HON","stockName":"Honeywell"},{"stockTicker":"MO","stockName":"Altria"},{"stockTicker":"BTI","stockName":"British American Tobacco"},{"stockTicker":"MMM","stockName":"3M"},{"stockTicker":"UTX","stockName":"United Technologies"},{"stockTicker":"GS","stockName":"Goldman Sachs"},{"stockTicker":"MS","stockName":"Morgan Stanley"},{"stockTicker":"AXP","stockName":"american express"},{"stockTicker":"CAT","stockName":"Caterpillar"},{"stockTicker":"CVS","stockName":"CVS Health Corp."},{"stockTicker":"FOX","stockName":"Fox Inc."},{"stockTicker":"ABEV","stockName":"Ambev"},{"stockTicker":"KHC","stockName":"Kraft Heinz"},{"stockTicker":"FDX","stockName":"FedEx"},{"stockTicker":"AGN","stockName":"Allergan"},{"stockTicker":"CL","stockName":"Colgate-Palmolive"},{"stockTicker":"AABA","stockName":"Altaba"},{"stockTicker":"AMD","stockName":"Advanced Micro Devices"},{"stockTicker":"CRON","stockName":"Cronos Group"},{"stockTicker":"MU","stockName":"Micron"},{"stockTicker":"ACN","stockName":"Accenture"},{"stockTicker":"CRM","stockName":"Salesforce.com"},{"stockTicker":"UPS","stockName":"United Parcel"},{"stockTicker":"SLB","stockName":"Schlumberger"},{"stockTicker":"VALE","stockName":"Vale"},{"stockTicker":"EXC","stockName":"Exelon"},{"stockTicker":"DAL","stockName":"Delta Air Lines"},{"stockTicker":"AIG","stockName":"American International Group"},{"stockTicker":"SO","stockName":"Southern"},{"stockTicker":"SQ","stockName":"Square"},{"stockTicker":"KMI","stockName":"Kinder Morgan"},{"stockTicker":"MPC","stockName":"Marathon Petroleum"},{"stockTicker":"MRK","stockName":"Merck & Company"},{"stockTicker":"AMGN","stockName":"Amgen"},{"stockTicker":"CELG","stockName":"Celgene"},{"stockTicker":"OXY","stockName":"Occidental Petroleum"},{"stockTicker":"DUK","stockName":"Duke Energy Corp"},{"stockTicker":"BSX","stockName":"Boston Scientific"},{"stockTicker":"CTSH","stockName":"Cognizant Technology Solutions"},{"stockTicker":"EBAY","stockName":"Ebay"},{"stockTicker":"EA","stockName":"Electronic Arts"}]